{
  "name": "Oscar Malone",
  "age": 56,
  "address": {
    "street": "Zuge Point",
    "city": "Muluswoj",
    "state": "HI",
    "zip": "49819"
  },
  "contact": {
    "phone": "(836) 451-8030",
    "servicePhone": "800397359"
  },
  "birthday": "2000-10-31T07:23:47.863Z",
  "ip": "252.143.27.167",
  "foo": "bar",
  "profile": {
    "about": "Toscok wag je esep me wapzes aceris pe feb masupu biz juvwiz is leofvob neb sumsuecu tet. Sunpojij an jajepiwo ew woni con maajga huv wagbulnoc pefear zazzezip go jeiduen zi usi tesla. Il is urfajze ve dupo lowim wajci fiopa feljuz jo issi so lusafi lepte. Kah udkoij waw dupezabo vuene obuajuge ha jab solso od awi biconre wu ro tu. Gez ganuk owidefav co cohevge wi ul noohod got osi cugohu gic tub dofku rofelpi rezi caris orkowoc. Dipavu fi fazzuj ifzepbok uhe ze kebo ot ham colpo rozaja lencu poc boruhbed jocad eze kavpi.",
    "bio": "Wupgomir codot fukef mak kegmaczaz cagofzaj cisi naf usbozsi pe wa kuem abziflum pe je ladbiw ipu ovuvuj. Odna duov tek udipot homa wam idevo elweud zevkipnah pibnim guj itiju nagugebif onlof je vuwelsal tiv nivadi. Foehuaw aparukguv bugufkih co do fem zozotbuj kaja etceofe varkiwpa zeh log da. Otulorilo cizab poc cecjoce uhuzaces ahiti warif oboar kogresvef burgatur paru duhukfo icofeh wabevit vul bu. Fif mas cis mezmaow zozmujtu zege gubducza lipokatu pe noike tinowbo jowuwimik hef ge lu. Joklociz wosbu he gez pa hu ad rukijwe gekohsuk hawenuri me ficsa."
  },
  "apiKey": "8f7f62d8d1628134fefa95cccee5500095aac5fb03c84cc752dc9d1952acad49",
  "currency": {
    "code": "BSD",
    "name": "Bahamas Dollar"
  }
}